snow_pc/__init__.py
snow_pc/align.py
snow_pc/common.py
snow_pc/filtering.py
snow_pc/modeling.py
snow_pc/prepare.py
snow_pc/snow_pc.py
snow_pc-0.2.0.dist-info/LICENSE
snow_pc-0.2.0.dist-info/METADATA
snow_pc-0.2.0.dist-info/WHEEL
snow_pc-0.2.0.dist-info/dependency_links.txt
snow_pc-0.2.0.dist-info/top_level.txt
snow_pc-0.2.0.dist-info/RECORD
