Metadata-Version: 2.1
Name: snow-pc
Version: 0.2.0
Summary: A python package for automated processing of point clouds to simplify elevation creation, co-registration and differencing to facilitate the production of snow depth and vegetation products.
Home-page: https://github.com/Surfix/snow-pc
Author: Naheem Adebisi
Author-email: adebisi.naheem@gmail.com
License: MIT license
Keywords: snow_pc
Classifier: Intended Audience :: Developers
Classifier: License :: OSI Approved :: MIT License
Classifier: Natural Language :: English
Classifier: Programming Language :: Python :: 3
Classifier: Programming Language :: Python :: 3.8
Classifier: Programming Language :: Python :: 3.9
Classifier: Programming Language :: Python :: 3.10
Classifier: Programming Language :: Python :: 3.11
Requires-Python: >=3.8
License-File: LICENSE
Requires-Dist: folium
Requires-Dist: ipyleaflet
Requires-Dist: python-pdal
Requires-Dist: rioxarray
Requires-Dist: py3dep
Requires-Dist: shapely
Requires-Dist: docopt
Requires-Dist: matplotlib
Requires-Dist: geopandas
Requires-Dist: rasterio
Requires-Dist: xarray
Requires-Dist: pandas
Requires-Dist: laspy
Requires-Dist: leafmap
